pigeonhole/__init__.py
pigeonhole/plugin.py
pytest_pigeonhole-0.3.1.dist-info/METADATA
pytest_pigeonhole-0.3.1.dist-info/RECORD
pytest_pigeonhole-0.3.1.dist-info/WHEEL
pytest_pigeonhole-0.3.1.dist-info/entry_points.txt
pytest_pigeonhole-0.3.1.dist-info/top_level.txt
