Metadata-Version: 2.1
Name: pytest-pigeonhole
Version: 0.3.1
Summary: UNKNOWN
Home-page: https://gitlab.com/kamichal/pigeonhole
Author: Michal Kaczmarczyk
Author-email: michal.s.kaczmarczyk@gmail.com
License: UNKNOWN
Platform: UNKNOWN
Classifier: Development Status :: 5 - Production/Stable
Classifier: Framework :: Pytest
Classifier: Intended Audience :: Developers
Classifier: Programming Language :: Python :: 2.7
Classifier: Programming Language :: Python :: 3.5
Classifier: Programming Language :: Python :: 3.6
Classifier: Programming Language :: Python :: 3.7
Classifier: Programming Language :: Python :: Implementation :: PyPy
Classifier: Programming Language :: Python
Classifier: Topic :: Software Development :: Testing
Requires-Dist: pytest (>=3.4)
